lyra2re2_hash.cp39-win_amd64.pyd
lyra2re3_hash.cp39-win_amd64.pyd
lyra2re_hash.cp39-win_amd64.pyd
lyra2re2_hash_test-0.0.2.dist-info/LICENSE
lyra2re2_hash_test-0.0.2.dist-info/METADATA
lyra2re2_hash_test-0.0.2.dist-info/WHEEL
lyra2re2_hash_test-0.0.2.dist-info/top_level.txt
lyra2re2_hash_test-0.0.2.dist-info/RECORD
