Metadata-Version: 2.1
Name: lyra2re2-hash-test
Version: 0.0.2
Summary: Bindings for Lyra2RE* proof of work used by Vertcoin
Home-page: https://github.com/vertiond/lyra2re-hash-python
Author: vertion
Author-email: vertion@protonmail.com
License: UNKNOWN
Platform: UNKNOWN
License-File: LICENSE
